utils_sscha_mlip/Cluster_Management.py
utils_sscha_mlip/MTP_environment.py
utils_sscha_mlip/__init__.py
utils_sscha_mlip/utils.py
utils_sscha_mlip-0.3.dist-info/METADATA
utils_sscha_mlip-0.3.dist-info/WHEEL
utils_sscha_mlip-0.3.dist-info/top_level.txt
utils_sscha_mlip-0.3.dist-info/RECORD
