Metadata-Version: 2.1
Name: utils_sscha_mlip
Version: 0.3
Summary: MTP package for SSCHA
Author: Francesco Belli
Author-email: <bellifra93@gmail.com>
Keywords: python,SSCHA_MLIP
Classifier: Development Status :: 3 - Alpha
Classifier: Programming Language :: Python :: 3
Requires-Dist: python-sscha
Requires-Dist: CellConstructor
